pypi_sandbox/__init__.py
pypi_sandbox-0.0.0.dist-info/DESCRIPTION.rst
pypi_sandbox-0.0.0.dist-info/METADATA
pypi_sandbox-0.0.0.dist-info/RECORD
pypi_sandbox-0.0.0.dist-info/WHEEL
pypi_sandbox-0.0.0.dist-info/metadata.json
pypi_sandbox-0.0.0.dist-info/top_level.txt
