Metadata-Version: 2.0
Name: pypi-sandbox
Version: 0.0.0
Summary: A micro project for dorking around with pypi
Home-page: https://github.com/mattfinnell/pypi-sandbox
Author: Matt Finnell
Author-email: mattfinnell104@gmail.com
License: MIT
Platform: UNKNOWN
